LICENSE
MANIFEST.in
README.md
setup.cfg
setup.py
notifications/__init__.py
notifications/cron.py
notifications/models.py
notifications/querysets.py
notifications/urls.py
notifications/views.py
notifications/migrations/0001_initial.py
notifications/migrations/0002_auto_20171020_0913.py
notifications/migrations/0003_auto_20180403_1606.py
notifications/migrations/0004_auto_20190225_1021.py
notifications/migrations/0005_notification_email.py
notifications/migrations/__init__.py
notifications/templates/email/notifications/notification.html
notifications/templates/notifications/notification_detail.html
notifications/templates/notifications/notification_list.html
podiant_notifications.egg-info/PKG-INFO
podiant_notifications.egg-info/SOURCES.txt
podiant_notifications.egg-info/dependency_links.txt
podiant_notifications.egg-info/not-zip-safe
podiant_notifications.egg-info/requires.txt
podiant_notifications.egg-info/top_level.txt