Metadata-Version: 2.1
Name: podiant-notifications
Version: 1.1.1
Summary: A set of models, views and templates for creating and managing user notifications
Home-page: https://git.steadman.io/podiant/notifications
Author: Mark Steadman
Author-email: mark@podiant.co
License: MIT
Keywords: podiant-notifications
Platform: UNKNOWN
Classifier: Development Status :: 3 - Alpha
Classifier: Framework :: Django :: 1.11
Classifier: Intended Audience :: Developers
Classifier: License :: OSI Approved :: BSD License
Classifier: Natural Language :: English
Classifier: Programming Language :: Python :: 3
Classifier: Programming Language :: Python :: 3.4
Classifier: Programming Language :: Python :: 3.5
Classifier: Programming Language :: Python :: 3.6
